{
    "epochs": [
        [
            {
                "epoch": 0,
                "loss": 2.509423712083385,
                "time": 7.359421491622925
            },
            {
                "epoch": 1,
                "loss": 2.5013911279580583,
                "time": 6.914879322052002
            },
            {
                "epoch": 2,
                "loss": 2.493115401999536,
                "time": 6.940778732299805
            },
            {
                "epoch": 3,
                "loss": 2.494935920690084,
                "time": 6.990268230438232
            },
            {
                "epoch": 4,
                "loss": 2.4873233681673255,
                "time": 6.923405170440674
            },
            {
                "epoch": 5,
                "loss": 2.4901170238529,
                "time": 7.078188419342041
            },
            {
                "epoch": 6,
                "loss": 2.4785992369418572,
                "time": 6.896975994110107
            },
            {
                "epoch": 7,
                "loss": 2.475700738735906,
                "time": 7.0639636516571045
            },
            {
                "epoch": 8,
                "loss": 2.4828733269515233,
                "time": 6.906689882278442
            },
            {
                "epoch": 9,
                "loss": 2.4735860686281725,
                "time": 6.884463548660278
            },
            {
                "epoch": 10,
                "loss": 2.472271256935708,
                "time": 6.949672222137451
            },
            {
                "epoch": 11,
                "loss": 2.4663474054377246,
                "time": 6.956317186355591
            },
            {
                "epoch": 12,
                "loss": 2.4632721313423684,
                "time": 6.881687164306641
            },
            {
                "epoch": 13,
                "loss": 2.4611866140418694,
                "time": 6.885112524032593
            },
            {
                "epoch": 14,
                "loss": 2.459095140821853,
                "time": 6.934962749481201
            },
            {
                "epoch": 15,
                "loss": 2.4549455684988613,
                "time": 6.9620420932769775
            },
            {
                "epoch": 16,
                "loss": 2.458020750052731,
                "time": 6.895705223083496
            },
            {
                "epoch": 17,
                "loss": 2.4529238889288907,
                "time": 6.937160491943359
            },
            {
                "epoch": 18,
                "loss": 2.452714942004203,
                "time": 6.936977386474609
            },
            {
                "epoch": 19,
                "loss": 2.4509616067377493,
                "time": 6.904439210891724
            },
            {
                "epoch": 20,
                "loss": 2.4525955595682443,
                "time": 6.894804000854492
            },
            {
                "epoch": 21,
                "loss": 2.4479245379472347,
                "time": 6.93304181098938
            },
            {
                "epoch": 22,
                "loss": 2.448295392248428,
                "time": 6.9571311473846436
            },
            {
                "epoch": 23,
                "loss": 2.442672657741481,
                "time": 6.899705648422241
            },
            {
                "epoch": 24,
                "loss": 2.4424835397104827,
                "time": 6.9298577308654785
            },
            {
                "epoch": 25,
                "loss": 2.439438818309855,
                "time": 6.891259670257568
            },
            {
                "epoch": 26,
                "loss": 2.434209919641607,
                "time": 6.926562309265137
            },
            {
                "epoch": 27,
                "loss": 2.440785822973706,
                "time": 6.962523937225342
            },
            {
                "epoch": 28,
                "loss": 2.4384130262724875,
                "time": 6.916863441467285
            },
            {
                "epoch": 29,
                "loss": 2.438183887960989,
                "time": 7.517908096313477
            }
        ],
        [
            {
                "epoch": 0,
                "loss": 2.437827730478377,
                "time": 7.728524208068848
            },
            {
                "epoch": 1,
                "loss": 2.4349202717970315,
                "time": 7.847951173782349
            },
            {
                "epoch": 2,
                "loss": 2.435590003639705,
                "time": 7.046117305755615
            },
            {
                "epoch": 3,
                "loss": 2.432565103839104,
                "time": 7.364396333694458
            },
            {
                "epoch": 4,
                "loss": 2.433567145427583,
                "time": 7.157445430755615
            },
            {
                "epoch": 5,
                "loss": 2.4313955063598804,
                "time": 6.770185947418213
            },
            {
                "epoch": 6,
                "loss": 2.4266559656802964,
                "time": 6.66115927696228
            },
            {
                "epoch": 7,
                "loss": 2.4280787909043613,
                "time": 6.642092704772949
            },
            {
                "epoch": 8,
                "loss": 2.4272603476149723,
                "time": 6.6210267543792725
            },
            {
                "epoch": 9,
                "loss": 2.4276050894445014,
                "time": 6.679783821105957
            },
            {
                "epoch": 10,
                "loss": 2.428843941946011,
                "time": 6.655155420303345
            },
            {
                "epoch": 11,
                "loss": 2.4194488377747327,
                "time": 6.841929912567139
            },
            {
                "epoch": 12,
                "loss": 2.425798902407106,
                "time": 6.839865446090698
            },
            {
                "epoch": 13,
                "loss": 2.4230860959649956,
                "time": 6.730998992919922
            },
            {
                "epoch": 14,
                "loss": 2.423475280084843,
                "time": 6.681537866592407
            },
            {
                "epoch": 15,
                "loss": 2.42117413330021,
                "time": 6.73530912399292
            },
            {
                "epoch": 16,
                "loss": 2.4155993759948644,
                "time": 6.701898574829102
            },
            {
                "epoch": 17,
                "loss": 2.4237560657387913,
                "time": 6.709275484085083
            },
            {
                "epoch": 18,
                "loss": 2.417271256186591,
                "time": 6.692345857620239
            },
            {
                "epoch": 19,
                "loss": 2.422159509571664,
                "time": 6.670939922332764
            },
            {
                "epoch": 20,
                "loss": 2.4137415032789336,
                "time": 7.0242156982421875
            },
            {
                "epoch": 21,
                "loss": 2.416488512821369,
                "time": 6.67655348777771
            },
            {
                "epoch": 22,
                "loss": 2.418829640431606,
                "time": 6.6628577709198
            },
            {
                "epoch": 23,
                "loss": 2.4150567322653083,
                "time": 6.70924711227417
            },
            {
                "epoch": 24,
                "loss": 2.4146856971249244,
                "time": 6.651811122894287
            },
            {
                "epoch": 25,
                "loss": 2.410962277389073,
                "time": 6.668123960494995
            },
            {
                "epoch": 26,
                "loss": 2.4139184597938352,
                "time": 6.653897523880005
            },
            {
                "epoch": 27,
                "loss": 2.4150822637388702,
                "time": 6.677110433578491
            },
            {
                "epoch": 28,
                "loss": 2.4131384080671943,
                "time": 7.143081188201904
            },
            {
                "epoch": 29,
                "loss": 2.409562175428374,
                "time": 7.582747459411621
            }
        ],
        [
            {
                "epoch": 0,
                "loss": 2.4093873436898114,
                "time": 7.037705898284912
            },
            {
                "epoch": 1,
                "loss": 2.411090857533178,
                "time": 7.135328054428101
            },
            {
                "epoch": 2,
                "loss": 2.4064364760393095,
                "time": 6.952447175979614
            },
            {
                "epoch": 3,
                "loss": 2.409192144051928,
                "time": 7.165379524230957
            },
            {
                "epoch": 4,
                "loss": 2.410392693497688,
                "time": 7.359920978546143
            },
            {
                "epoch": 5,
                "loss": 2.41130358328212,
                "time": 7.89428973197937
            },
            {
                "epoch": 6,
                "loss": 2.4101970375112076,
                "time": 7.918924808502197
            },
            {
                "epoch": 7,
                "loss": 2.4068870881885,
                "time": 8.434691667556763
            },
            {
                "epoch": 8,
                "loss": 2.4054666119105246,
                "time": 7.976402521133423
            },
            {
                "epoch": 9,
                "loss": 2.4078836363840006,
                "time": 7.656293630599976
            },
            {
                "epoch": 10,
                "loss": 2.404451696360584,
                "time": 7.138031959533691
            },
            {
                "epoch": 11,
                "loss": 2.407183661271083,
                "time": 7.187547206878662
            },
            {
                "epoch": 12,
                "loss": 2.4058765351867777,
                "time": 7.054368257522583
            },
            {
                "epoch": 13,
                "loss": 2.4023343625816156,
                "time": 7.123938322067261
            },
            {
                "epoch": 14,
                "loss": 2.4071520491055662,
                "time": 7.055225372314453
            },
            {
                "epoch": 15,
                "loss": 2.403021587793593,
                "time": 7.051124811172485
            },
            {
                "epoch": 16,
                "loss": 2.4014361314056583,
                "time": 7.079397439956665
            },
            {
                "epoch": 17,
                "loss": 2.400995914029225,
                "time": 7.073884010314941
            },
            {
                "epoch": 18,
                "loss": 2.403337767594339,
                "time": 6.7746970653533936
            },
            {
                "epoch": 19,
                "loss": 2.402939814306869,
                "time": 6.7319934368133545
            },
            {
                "epoch": 20,
                "loss": 2.397485307186086,
                "time": 6.755419015884399
            },
            {
                "epoch": 21,
                "loss": 2.403663312966085,
                "time": 6.743081331253052
            },
            {
                "epoch": 22,
                "loss": 2.399479002751468,
                "time": 6.8147077560424805
            },
            {
                "epoch": 23,
                "loss": 2.4027967699774893,
                "time": 6.794010162353516
            },
            {
                "epoch": 24,
                "loss": 2.402184498072932,
                "time": 7.138559579849243
            },
            {
                "epoch": 25,
                "loss": 2.4000269606665516,
                "time": 7.292407035827637
            },
            {
                "epoch": 26,
                "loss": 2.396835473286567,
                "time": 7.137651205062866
            },
            {
                "epoch": 27,
                "loss": 2.398694614535057,
                "time": 7.344619274139404
            },
            {
                "epoch": 28,
                "loss": 2.3998220013164304,
                "time": 8.087790250778198
            },
            {
                "epoch": 29,
                "loss": 2.3930881697653064,
                "time": 7.767314195632935
            }
        ],
        [
            {
                "epoch": 0,
                "loss": 2.3973438523071695,
                "time": 7.6021199226379395
            },
            {
                "epoch": 1,
                "loss": 2.3986506383305572,
                "time": 7.0253942012786865
            },
            {
                "epoch": 2,
                "loss": 2.396089891332285,
                "time": 7.754827260971069
            },
            {
                "epoch": 3,
                "loss": 2.3955021220965085,
                "time": 8.246618747711182
            },
            {
                "epoch": 4,
                "loss": 2.3986376156609555,
                "time": 7.450993776321411
            },
            {
                "epoch": 5,
                "loss": 2.3948393559287577,
                "time": 7.133453607559204
            },
            {
                "epoch": 6,
                "loss": 2.3973085241629732,
                "time": 7.173172950744629
            },
            {
                "epoch": 7,
                "loss": 2.3955425259369387,
                "time": 7.420583963394165
            },
            {
                "epoch": 8,
                "loss": 2.3959833821811927,
                "time": 7.33679461479187
            },
            {
                "epoch": 9,
                "loss": 2.395802669462078,
                "time": 7.519984006881714
            },
            {
                "epoch": 10,
                "loss": 2.3943458084167037,
                "time": 7.407710313796997
            },
            {
                "epoch": 11,
                "loss": 2.390777010286911,
                "time": 6.843186140060425
            },
            {
                "epoch": 12,
                "loss": 2.391850340721655,
                "time": 7.047433614730835
            },
            {
                "epoch": 13,
                "loss": 2.3940338585985277,
                "time": 7.7878477573394775
            },
            {
                "epoch": 14,
                "loss": 2.3943224903270606,
                "time": 7.3005712032318115
            },
            {
                "epoch": 15,
                "loss": 2.391300733565958,
                "time": 7.271310567855835
            },
            {
                "epoch": 16,
                "loss": 2.3947288812788834,
                "time": 7.045848846435547
            },
            {
                "epoch": 17,
                "loss": 2.3895704396740025,
                "time": 7.455325365066528
            },
            {
                "epoch": 18,
                "loss": 2.3913271071553592,
                "time": 7.550698280334473
            },
            {
                "epoch": 19,
                "loss": 2.388578926378788,
                "time": 7.105334758758545
            },
            {
                "epoch": 20,
                "loss": 2.3923528708778767,
                "time": 7.678500175476074
            },
            {
                "epoch": 21,
                "loss": 2.391459446068287,
                "time": 7.378267288208008
            },
            {
                "epoch": 22,
                "loss": 2.3900134223237623,
                "time": 7.301687479019165
            },
            {
                "epoch": 23,
                "loss": 2.391229819305722,
                "time": 7.413692235946655
            },
            {
                "epoch": 24,
                "loss": 2.390387792630068,
                "time": 7.23678731918335
            },
            {
                "epoch": 25,
                "loss": 2.3893328297370324,
                "time": 7.34381365776062
            },
            {
                "epoch": 26,
                "loss": 2.389717790211109,
                "time": 7.262066125869751
            },
            {
                "epoch": 27,
                "loss": 2.3902691482341893,
                "time": 6.900146245956421
            },
            {
                "epoch": 28,
                "loss": 2.3888553975741083,
                "time": 6.648968458175659
            },
            {
                "epoch": 29,
                "loss": 2.3881816643291347,
                "time": 6.705986738204956
            }
        ],
        [
            {
                "epoch": 0,
                "loss": 2.388976341475116,
                "time": 7.219697713851929
            },
            {
                "epoch": 1,
                "loss": 2.389961759426569,
                "time": 7.738292455673218
            },
            {
                "epoch": 2,
                "loss": 2.3858764725475377,
                "time": 7.6750547885894775
            },
            {
                "epoch": 3,
                "loss": 2.3837623522671776,
                "time": 7.984673500061035
            },
            {
                "epoch": 4,
                "loss": 2.385202647352522,
                "time": 7.520367383956909
            },
            {
                "epoch": 5,
                "loss": 2.3873146640267784,
                "time": 7.34297251701355
            },
            {
                "epoch": 6,
                "loss": 2.3847662044896087,
                "time": 7.5199806690216064
            },
            {
                "epoch": 7,
                "loss": 2.3877012344427113,
                "time": 7.041252136230469
            },
            {
                "epoch": 8,
                "loss": 2.38549924619457,
                "time": 6.850758075714111
            },
            {
                "epoch": 9,
                "loss": 2.385649929295002,
                "time": 6.766351699829102
            },
            {
                "epoch": 10,
                "loss": 2.387068842071896,
                "time": 6.8034751415252686
            },
            {
                "epoch": 11,
                "loss": 2.386000870445007,
                "time": 6.787534236907959
            },
            {
                "epoch": 12,
                "loss": 2.3835798385968605,
                "time": 8.72732949256897
            },
            {
                "epoch": 13,
                "loss": 2.3862555991577126,
                "time": 7.075416088104248
            },
            {
                "epoch": 14,
                "loss": 2.3835276766881193,
                "time": 6.902011394500732
            },
            {
                "epoch": 15,
                "loss": 2.382414383877528,
                "time": 7.408498525619507
            },
            {
                "epoch": 16,
                "loss": 2.3821538115543364,
                "time": 7.707552433013916
            },
            {
                "epoch": 17,
                "loss": 2.3870990173121465,
                "time": 7.735547780990601
            },
            {
                "epoch": 18,
                "loss": 2.3803931387001698,
                "time": 9.127434253692627
            },
            {
                "epoch": 19,
                "loss": 2.382731053233432,
                "time": 6.9945454597473145
            },
            {
                "epoch": 20,
                "loss": 2.3849938555646704,
                "time": 7.001480579376221
            },
            {
                "epoch": 21,
                "loss": 2.3852642650080162,
                "time": 7.300435304641724
            },
            {
                "epoch": 22,
                "loss": 2.381495996976397,
                "time": 7.035001754760742
            },
            {
                "epoch": 23,
                "loss": 2.3821867256738383,
                "time": 7.214468002319336
            },
            {
                "epoch": 24,
                "loss": 2.381044338973551,
                "time": 6.884098052978516
            },
            {
                "epoch": 25,
                "loss": 2.3815339353064022,
                "time": 6.978814363479614
            },
            {
                "epoch": 26,
                "loss": 2.3802937052671473,
                "time": 7.02032995223999
            },
            {
                "epoch": 27,
                "loss": 2.3783658279118884,
                "time": 7.07381796836853
            },
            {
                "epoch": 28,
                "loss": 2.3802000519048714,
                "time": 7.076751470565796
            },
            {
                "epoch": 29,
                "loss": 2.3800344063552132,
                "time": 7.016013145446777
            }
        ]
    ],
    "test_metrics": {
        "accuracy": 0.1009,
        "precision": 0.0829086741296323,
        "recall": 0.1009,
        "f1_score": 0.054783944480730165,
        "confusion_matrix": [
            [
                681,
                57,
                61,
                3,
                131,
                3,
                1,
                1,
                1,
                61
            ],
            [
                644,
                101,
                71,
                6,
                94,
                3,
                2,
                7,
                9,
                63
            ],
            [
                718,
                103,
                50,
                0,
                50,
                3,
                0,
                0,
                3,
                73
            ],
            [
                666,
                122,
                102,
                1,
                38,
                1,
                2,
                4,
                4,
                60
            ],
            [
                709,
                90,
                54,
                3,
                55,
                2,
                0,
                1,
                2,
                84
            ],
            [
                734,
                100,
                75,
                1,
                37,
                0,
                1,
                0,
                8,
                44
            ],
            [
                605,
                128,
                103,
                0,
                28,
                3,
                1,
                2,
                4,
                126
            ],
            [
                609,
                96,
                60,
                3,
                113,
                5,
                4,
                3,
                2,
                105
            ],
            [
                658,
                58,
                29,
                5,
                209,
                0,
                1,
                3,
                5,
                32
            ],
            [
                523,
                66,
                75,
                4,
                207,
                0,
                1,
                9,
                3,
                112
            ]
        ]
    },
    "fold_results": [
        {
            "accuracy": 0.0915,
            "precision": 0.07816659271093722,
            "recall": 0.0915,
            "f1_score": 0.050099064752041046,
            "confusion_matrix": [
                [
                    587,
                    87,
                    24,
                    0,
                    242,
                    0,
                    0,
                    0,
                    0,
                    33
                ],
                [
                    574,
                    117,
                    57,
                    0,
                    181,
                    0,
                    0,
                    0,
                    1,
                    49
                ],
                [
                    722,
                    105,
                    49,
                    0,
                    113,
                    0,
                    0,
                    0,
                    1,
                    40
                ],
                [
                    738,
                    109,
                    55,
                    0,
                    75,
                    0,
                    0,
                    0,
                    0,
                    46
                ],
                [
                    629,
                    133,
                    32,
                    0,
                    93,
                    0,
                    0,
                    0,
                    0,
                    46
                ],
                [
                    767,
                    104,
                    51,
                    0,
                    62,
                    0,
                    0,
                    0,
                    0,
                    31
                ],
                [
                    681,
                    129,
                    59,
                    0,
                    59,
                    0,
                    0,
                    1,
                    0,
                    67
                ],
                [
                    606,
                    107,
                    39,
                    0,
                    176,
                    1,
                    0,
                    0,
                    0,
                    65
                ],
                [
                    534,
                    68,
                    15,
                    0,
                    385,
                    0,
                    0,
                    0,
                    1,
                    14
                ],
                [
                    517,
                    80,
                    29,
                    0,
                    345,
                    0,
                    0,
                    0,
                    1,
                    68
                ]
            ]
        },
        {
            "accuracy": 0.0926,
            "precision": 0.09409952966647456,
            "recall": 0.0926,
            "f1_score": 0.0494857726744364,
            "confusion_matrix": [
                [
                    622,
                    73,
                    24,
                    0,
                    221,
                    1,
                    0,
                    0,
                    0,
                    59
                ],
                [
                    594,
                    115,
                    67,
                    1,
                    154,
                    0,
                    0,
                    0,
                    1,
                    68
                ],
                [
                    723,
                    100,
                    39,
                    0,
                    71,
                    0,
                    0,
                    0,
                    0,
                    46
                ],
                [
                    708,
                    108,
                    71,
                    1,
                    58,
                    1,
                    1,
                    0,
                    0,
                    70
                ],
                [
                    712,
                    105,
                    53,
                    1,
                    69,
                    0,
                    0,
                    0,
                    0,
                    71
                ],
                [
                    773,
                    92,
                    43,
                    0,
                    58,
                    1,
                    0,
                    2,
                    2,
                    47
                ],
                [
                    611,
                    117,
                    86,
                    0,
                    42,
                    1,
                    0,
                    0,
                    1,
                    86
                ],
                [
                    590,
                    118,
                    56,
                    2,
                    150,
                    0,
                    0,
                    0,
                    0,
                    83
                ],
                [
                    632,
                    39,
                    17,
                    5,
                    306,
                    1,
                    0,
                    1,
                    1,
                    26
                ],
                [
                    505,
                    85,
                    59,
                    0,
                    272,
                    0,
                    0,
                    3,
                    1,
                    78
                ]
            ]
        },
        {
            "accuracy": 0.097,
            "precision": 0.10058403729460741,
            "recall": 0.097,
            "f1_score": 0.0524115571221262,
            "confusion_matrix": [
                [
                    650,
                    67,
                    50,
                    2,
                    167,
                    0,
                    1,
                    1,
                    0,
                    43
                ],
                [
                    645,
                    109,
                    69,
                    2,
                    139,
                    2,
                    1,
                    4,
                    2,
                    75
                ],
                [
                    712,
                    107,
                    56,
                    1,
                    62,
                    1,
                    0,
                    1,
                    2,
                    65
                ],
                [
                    686,
                    106,
                    68,
                    0,
                    60,
                    0,
                    0,
                    1,
                    0,
                    70
                ],
                [
                    688,
                    109,
                    62,
                    0,
                    54,
                    1,
                    0,
                    1,
                    0,
                    84
                ],
                [
                    735,
                    113,
                    63,
                    0,
                    45,
                    1,
                    0,
                    0,
                    2,
                    39
                ],
                [
                    652,
                    125,
                    104,
                    0,
                    33,
                    2,
                    1,
                    0,
                    2,
                    107
                ],
                [
                    591,
                    96,
                    59,
                    1,
                    122,
                    2,
                    0,
                    0,
                    2,
                    113
                ],
                [
                    610,
                    46,
                    20,
                    0,
                    259,
                    0,
                    0,
                    0,
                    2,
                    31
                ],
                [
                    527,
                    87,
                    53,
                    2,
                    227,
                    0,
                    1,
                    1,
                    1,
                    97
                ]
            ]
        },
        {
            "accuracy": 0.0997,
            "precision": 0.10343357370445083,
            "recall": 0.0997,
            "f1_score": 0.05563043463069342,
            "confusion_matrix": [
                [
                    664,
                    99,
                    49,
                    3,
                    155,
                    2,
                    0,
                    1,
                    1,
                    62
                ],
                [
                    636,
                    92,
                    68,
                    1,
                    107,
                    0,
                    1,
                    4,
                    3,
                    72
                ],
                [
                    677,
                    115,
                    70,
                    1,
                    50,
                    3,
                    1,
                    1,
                    3,
                    70
                ],
                [
                    675,
                    111,
                    86,
                    2,
                    53,
                    1,
                    2,
                    0,
                    2,
                    69
                ],
                [
                    725,
                    112,
                    54,
                    0,
                    60,
                    0,
                    0,
                    2,
                    0,
                    93
                ],
                [
                    700,
                    112,
                    60,
                    0,
                    34,
                    0,
                    0,
                    0,
                    3,
                    56
                ],
                [
                    650,
                    116,
                    90,
                    0,
                    35,
                    4,
                    0,
                    1,
                    4,
                    101
                ],
                [
                    577,
                    96,
                    87,
                    2,
                    109,
                    1,
                    0,
                    2,
                    1,
                    100
                ],
                [
                    634,
                    55,
                    42,
                    1,
                    207,
                    0,
                    0,
                    4,
                    8,
                    32
                ],
                [
                    549,
                    67,
                    61,
                    3,
                    231,
                    1,
                    0,
                    4,
                    3,
                    99
                ]
            ]
        },
        {
            "accuracy": 0.0984,
            "precision": 0.08628345749930762,
            "recall": 0.0984,
            "f1_score": 0.05150005263118874,
            "confusion_matrix": [
                [
                    688,
                    62,
                    49,
                    5,
                    132,
                    3,
                    0,
                    2,
                    5,
                    64
                ],
                [
                    609,
                    101,
                    64,
                    2,
                    106,
                    1,
                    2,
                    9,
                    4,
                    91
                ],
                [
                    709,
                    81,
                    65,
                    0,
                    57,
                    5,
                    1,
                    3,
                    1,
                    71
                ],
                [
                    677,
                    85,
                    86,
                    2,
                    43,
                    2,
                    0,
                    4,
                    4,
                    64
                ],
                [
                    669,
                    126,
                    79,
                    0,
                    45,
                    3,
                    0,
                    3,
                    2,
                    84
                ],
                [
                    726,
                    108,
                    63,
                    0,
                    42,
                    0,
                    1,
                    2,
                    7,
                    55
                ],
                [
                    620,
                    150,
                    92,
                    0,
                    25,
                    1,
                    1,
                    3,
                    9,
                    132
                ],
                [
                    615,
                    127,
                    82,
                    1,
                    112,
                    6,
                    1,
                    2,
                    3,
                    97
                ],
                [
                    677,
                    57,
                    32,
                    4,
                    188,
                    1,
                    0,
                    2,
                    7,
                    36
                ],
                [
                    512,
                    72,
                    44,
                    8,
                    215,
                    1,
                    2,
                    11,
                    5,
                    73
                ]
            ]
        }
    ]
}